custom_py_docx/__init__.py
custom_py_docx/document.py
custom_py_docx-1.0.5.dist-info/LICENSE
custom_py_docx-1.0.5.dist-info/METADATA
custom_py_docx-1.0.5.dist-info/WHEEL
custom_py_docx-1.0.5.dist-info/RECORD
