Metadata-Version: 2.1
Name: custom_py_docx
Version: 1.0.5
Summary: Library to create DOCX facility using python-docx
License: BSD
Author: Renato Pinheiro
Author-email: renato.dev.pinheiro@gmail.com
Requires-Python: >=3.10,<4.0
Classifier: License :: Other/Proprietary License
Classifier: Programming Language :: Python :: 3
Classifier: Programming Language :: Python :: 3.10
Classifier: Programming Language :: Python :: 3.11
Classifier: Programming Language :: Python :: 3.12
Requires-Dist: babel (==2.12.1)
Requires-Dist: docxcompose (==1.4.0)
Requires-Dist: lxml (==4.9.2)
Requires-Dist: numpy (==1.24.3)
Requires-Dist: packaging (==23.1)
Requires-Dist: pandas (==2.0.1)
Requires-Dist: plotly (==5.14.1)
Requires-Dist: python-dateutil (==2.8.2)
Requires-Dist: python-docx (==0.8.11)
Requires-Dist: pytz (==2023.3)
Requires-Dist: six (==1.16.0)
Requires-Dist: tenacity (==8.2.2)
Requires-Dist: tzdata (==2023.3)
Project-URL: Bug Tracker, https://github.com/cristianovisk/custom-py-docx/issues
Project-URL: Código, https://github.com/cristianovisk/custom-py-docx
Project-URL: Documentação, https://github.com/cristianovisk/custom-py-docx/blob/main/README.md
